odoo/addons/stock_warehouse_orderpoint_stock_info_unreserved/README.rst
odoo/addons/stock_warehouse_orderpoint_stock_info_unreserved/__init__.py
odoo/addons/stock_warehouse_orderpoint_stock_info_unreserved/__manifest__.py
odoo/addons/stock_warehouse_orderpoint_stock_info_unreserved/i18n/de.po
odoo/addons/stock_warehouse_orderpoint_stock_info_unreserved/i18n/es.po
odoo/addons/stock_warehouse_orderpoint_stock_info_unreserved/i18n/es_ES.po
odoo/addons/stock_warehouse_orderpoint_stock_info_unreserved/i18n/pt_BR.po
odoo/addons/stock_warehouse_orderpoint_stock_info_unreserved/i18n/sl.po
odoo/addons/stock_warehouse_orderpoint_stock_info_unreserved/i18n/stock_warehouse_orderpoint_stock_info_unreserved.pot
odoo/addons/stock_warehouse_orderpoint_stock_info_unreserved/models/__init__.py
odoo/addons/stock_warehouse_orderpoint_stock_info_unreserved/models/stock_warehouse_orderpoint.py
odoo/addons/stock_warehouse_orderpoint_stock_info_unreserved/readme/CONTRIBUTORS.rst
odoo/addons/stock_warehouse_orderpoint_stock_info_unreserved/readme/DESCRIPTION.rst
odoo/addons/stock_warehouse_orderpoint_stock_info_unreserved/static/description/icon.png
odoo/addons/stock_warehouse_orderpoint_stock_info_unreserved/static/description/index.html
odoo/addons/stock_warehouse_orderpoint_stock_info_unreserved/tests/__init__.py
odoo/addons/stock_warehouse_orderpoint_stock_info_unreserved/tests/test_stock_warehouse_orderpoint.py
odoo/addons/stock_warehouse_orderpoint_stock_info_unreserved/views/stock_warehouse_orderpoint_view.xml
odoo12_addon_stock_warehouse_orderpoint_stock_info_unreserved-12.0.1.0.1.dist-info/METADATA
odoo12_addon_stock_warehouse_orderpoint_stock_info_unreserved-12.0.1.0.1.dist-info/WHEEL
odoo12_addon_stock_warehouse_orderpoint_stock_info_unreserved-12.0.1.0.1.dist-info/top_level.txt
odoo12_addon_stock_warehouse_orderpoint_stock_info_unreserved-12.0.1.0.1.dist-info/RECORD
